finx_ib_reports/__init__.py
finx_ib_reports/adapters.py
finx_ib_reports/config_helpers.py
finx_ib_reports/custom_flex_report.py
finx_ib_reports/date_helpers.py
finx_ib_reports/download_trades.py
finx_ib_reports-0.0.6.dist-info/LICENSE
finx_ib_reports-0.0.6.dist-info/METADATA
finx_ib_reports-0.0.6.dist-info/WHEEL
finx_ib_reports-0.0.6.dist-info/top_level.txt
finx_ib_reports-0.0.6.dist-info/RECORD
