Metadata-Version: 2.1
Name: finx-ib-reports
Version: 0.0.6
Summary: IBKR report data via ib_insync
Home-page: https://github.com/westonplatter/finx-ib-reports
Author: westonplatter
Author-email: westonplatter+finx@gmail.com
License: BSD-3
Project-URL: Issue Tracker, https://github.com/westonplatter/finx-ib-reports/issues
Project-URL: Source Code, https://github.com/westonplatter/finx-ib-reports
Platform: UNKNOWN
Requires-Python: >=3.6
License-File: LICENSE
Requires-Dist: ib-insync
Requires-Dist: loguru
Requires-Dist: pandas (<1.4,>=1.3.0)
Requires-Dist: numpy
Requires-Dist: pydantic
Requires-Dist: python-dotenv
Requires-Dist: pytz
Requires-Dist: requests
